README.md
license.txt
setup.py
tneb/__init__.py
tneb/bi_monthly_high.py
tneb/bi_monthly_low.py
tneb/monthly.py
tneb.egg-info/PKG-INFO
tneb.egg-info/SOURCES.txt
tneb.egg-info/dependency_links.txt
tneb.egg-info/top_level.txt