Metadata-Version: 2.1
Name: tneb
Version: 2.0
Summary: Tamil Nadu Electricity Bill Calculation Module For Domestic Supply
Author: ivankostark
Author-email: ivankostarkk@gmail.com
License-File: license.txt
